{
  "$schema": "http://json-schema.org/draft-04/schema#",
  "id": "http://www.behindmedia.com/schemas/Employee.json",
  "allOf": [
    {
      "$ref": "http://www.behindmedia.com/schemas/Person.json"
    },
    {
      "properties": {
        "employeeNumber": {
          "type": "string",
          "minLength": 10,
          "maxLength": 10,
          "readOnly": true
        }
      },
      "required": ["employeeNumber"]
    }
  ],
  "title": "com.behindmedia.Employee:com.behindmedia.Person",
  "type": "object"
}
